coldblue/__init__.py
coldblue/admin.py
coldblue/apps.py
coldblue/models.py
coldblue/tests.py
coldblue/views.py
coldblue/static/coldblue/css/theme.css
coldblue/templates/admin/base.html
coldblue/templates/admin/base_site.html
coldblue/templates/admin/change_list.html
coldblue/templates/admin/coldblue_stats.html
coldblue/templates/admin/index.html
coldblue/templates/admin/login.html
coldblue/templates/admin/includes/sidebar.html
coldblue/templatetags/__init__.py
coldblue/templatetags/coldblue_admin.py
coldblue/templatetags/coldblue_sidebar.py
coldblue-0.1.6.dist-info/licenses/LICENSE
coldblue-0.1.6.dist-info/METADATA
coldblue-0.1.6.dist-info/WHEEL
coldblue-0.1.6.dist-info/top_level.txt
coldblue-0.1.6.dist-info/RECORD
