Metadata-Version: 2.4
Name: coldblue
Version: 0.1.6
Summary: Modern dark theme for Django Admin
Author: JIYO P V
License-Expression: MIT
Project-URL: Homepage, https://github.com/jiyo-pv/coldblue
Project-URL: Repository, https://github.com/jiyo-pv/coldblue
Keywords: django,django-admin,admin-theme,dashboard
Classifier: Framework :: Django
Classifier: Framework :: Django :: 4.2
Classifier: Framework :: Django :: 5.0
Classifier: Operating System :: OS Independent
Classifier: Programming Language :: Python :: 3
Requires-Python: >=3.8
License-File: LICENSE
Requires-Dist: Django>=4.0
Dynamic: license-file
